.coveragerc
.gitignore
.isort.cfg
.pylintrc
.style.yapf
.travis.yml
HISTORY.md
LICENSE
MANIFEST.in
Makefile
README.md
mypy.ini
setup.cfg
setup.py
ossaudit/__init__.py
ossaudit/__main__.py
ossaudit/audit.py
ossaudit/cache.py
ossaudit/cli.py
ossaudit/const.py
ossaudit/option.py
ossaudit/packages.py
ossaudit.egg-info/PKG-INFO
ossaudit.egg-info/SOURCES.txt
ossaudit.egg-info/dependency_links.txt
ossaudit.egg-info/entry_points.txt
ossaudit.egg-info/requires.txt
ossaudit.egg-info/top_level.txt
requirements/README.md
requirements/requirements-dev-1.txt
requirements/requirements-dev-2.txt
requirements/requirements-dev-3.txt
requirements/requirements.txt
tests/__init__.py
tests/helpers.py
tests/test_audit.py
tests/test_cache.py
tests/test_cli.py
tests/test_option.py
tests/test_packages.py
tests/data/vulns01.json